{
  "id": "stability-pools",
  "title": "Stability Pools",
  "description": "Stability Pools are a core mechanism in Zhenglong that provides security, yield generation, and automated rebalancing capabilities.",
  "source": "@site/docs/stability-pools.md",
  "sourceDirName": ".",
  "slug": "/stability-pools",
  "permalink": "/stability-pools",
  "draft": false,
  "unlisted": false,
  "editUrl": "https://github.com/zhenglong-protocol/docs/tree/main/docs/stability-pools.md",
  "tags": [],
  "version": "current",
  "sidebarPosition": 3,
  "frontMatter": {
    "sidebar_position": 3
  },
  "sidebar": "tutorialSidebar",
  "previous": {
    "title": "Risk Considerations",
    "permalink": "/risk-considerations"
  },
  "next": {
    "title": "How Yield is Generated",
    "permalink": "/yield"
  }
}